{
    "sample": {
        "add": [
            1
        ],
        "edit": [
            1
        ],
        "list": [
            1
        ],
        "view": [
            1
        ]
    },
    "dev": {
        "error_list": [
            0
        ],
        "error_delete": [
            0
        ]
    },
    "user": {
        "add": [
            1,3
        ],
        "edit": [
            1,3
        ],
        "list": [
            1,3
        ],
        "view": [
            1,3
        ]
    }
}